setup.cfg
setup.py
fire/__init__.py
fire/completion.py
fire/completion_test.py
fire/core.py
fire/core_test.py
fire/decorators.py
fire/decorators_test.py
fire/fire_import_test.py
fire/fire_test.py
fire/helputils.py
fire/helputils_test.py
fire/inspectutils.py
fire/inspectutils_test.py
fire/interact.py
fire/interact_test.py
fire/parser.py
fire/parser_fuzz_test.py
fire/parser_test.py
fire/test_components.py
fire/test_components_py3.py
fire/test_components_test.py
fire/testutils.py
fire/testutils_test.py
fire/trace.py
fire/trace_test.py
fire.egg-info/PKG-INFO
fire.egg-info/SOURCES.txt
fire.egg-info/dependency_links.txt
fire.egg-info/pbr.json
fire.egg-info/requires.txt
fire.egg-info/top_level.txt